Metadata-Version: 2.1
Name: jsonMojo
Version: 0.1.0
Summary: A series of utility functions to help with tidy json via python dictionary.
Home-page: https://github.com/jienagu/jsonMojo
Author: Jiena Gu McLellan
Author-email: jienagu90@gmail.com
License: Apache License 2.0
Platform: UNKNOWN
